useful_tasks/__init__.py
useful_tasks/make_response.py
useful_tasks/utilities.py
gdev_powertools-0.0.1.dist-info/LICENSE
gdev_powertools-0.0.1.dist-info/METADATA
gdev_powertools-0.0.1.dist-info/WHEEL
gdev_powertools-0.0.1.dist-info/top_level.txt
gdev_powertools-0.0.1.dist-info/RECORD
