Metadata-Version: 2.1
Name: gdev-powertools
Version: 0.0.1
Summary: GDEV Powertools
Home-page: https://github.com/XXXXXXXXXXX/gdev-aws-powertools
Author-email: dolgasan@gmail.com
Keywords: aws,lambda
License-File: LICENSE
Requires-Dist: boto3
Requires-Dist: requests
